MANIFEST.in
README.md
pyproject.toml
setup.py
tactigon_speech_socket/__init__.py
tactigon_speech_socket/__main__.py
tactigon_speech_socket.egg-info/PKG-INFO
tactigon_speech_socket.egg-info/SOURCES.txt
tactigon_speech_socket.egg-info/dependency_links.txt
tactigon_speech_socket.egg-info/requires.txt
tactigon_speech_socket.egg-info/top_level.txt
tactigon_speech_socket/connection/__init__.py
tactigon_speech_socket/connection/client.py
tactigon_speech_socket/middleware/__init__.py
tactigon_speech_socket/middleware/packet_manager.c
tactigon_speech_socket/middleware/tactigon_speech.c
tactigon_speech_socket/models/__init__.py
tactigon_speech_socket/models/audio.py
tactigon_speech_socket/models/socket.py
tests/__init__.py
tests/audio_receive.py
tests/config.py
tests/setup_path.py
tests/tspeech.py