Metadata-Version: 2.1
Name: tactigon_speech_socket
Version: 5.5.0.2
Summary: Tactigon Speech Socket perform stt over a audio stream sent by socket.
Home-page: https://www.thetactigon.com
Maintainer: Next Industries s.r.l.
Maintainer-email: info@thetactigon.com
License: MIT
Keywords: tactigon,wereable,gestures controller,human interface,voice recognition,speech recognition,voice command,stt
Classifier: Programming Language :: Python :: 3
Classifier: Operating System :: OS Independent
Requires-Python: >=3.8.0,<3.9.0
Requires-Dist: deepspeech_tflite==0.9.3
